sphinx_rtd_theme_ext_color_contrast/__init__.py
sphinx_rtd_theme_ext_color_contrast/_version.py
sphinx_rtd_theme_ext_color_contrast/test_ext.py
sphinx_rtd_theme_ext_color_contrast/_static/sphinx_rtd_theme_ext_color_contrast.css
sphinx_rtd_theme_ext_color_contrast-0.3.2.dist-info/LICENSE
sphinx_rtd_theme_ext_color_contrast-0.3.2.dist-info/METADATA
sphinx_rtd_theme_ext_color_contrast-0.3.2.dist-info/WHEEL
sphinx_rtd_theme_ext_color_contrast-0.3.2.dist-info/top_level.txt
sphinx_rtd_theme_ext_color_contrast-0.3.2.dist-info/RECORD
