Metadata-Version: 2.1
Name: sphinx_rtd_theme_ext_color_contrast
Version: 0.3.2
Summary: sphinx_rtd_theme extension to enhance color contrast
Home-page: https://github.com/AaltoSciComp/sphinx_rtd_theme_ext_color_contrast/
Author: Richard Darst
Keywords: sphinx-extension
Classifier: Programming Language :: Python :: 3
Classifier: Development Status :: 4 - Beta
Classifier: Framework :: Sphinx
Classifier: Framework :: Sphinx :: Extension
Classifier: Operating System :: OS Independent
License-File: LICENSE
Requires-Dist: Sphinx
